sorbet/__init__.py
sorbet/color.py
sorbet/format_strings.py
sorbet/sorbet.py
sorbet-0.0.3.dist-info/LICENSE
sorbet-0.0.3.dist-info/METADATA
sorbet-0.0.3.dist-info/WHEEL
sorbet-0.0.3.dist-info/top_level.txt
sorbet-0.0.3.dist-info/RECORD
