Metadata-Version: 2.1
Name: sorbet
Version: 0.0.3
Summary: A better printing experience in the console.
Author: Himeji
Author-email: <himejidev@proton.me>
Keywords: python,print,icecream,log,debug,console,sorbet
Classifier: Development Status :: 1 - Planning
Classifier: Intended Audience :: Developers
Classifier: Programming Language :: Python :: 3
Classifier: Operating System :: Unix
Classifier: Operating System :: MacOS :: MacOS X
Classifier: Operating System :: Microsoft :: Windows
License-File: LICENSE
